artifact_map/__init__.py
artifact_map/module1.py
artifact_map/prompt_gen.py
artifact_map-0.3.dist-info/METADATA
artifact_map-0.3.dist-info/WHEEL
artifact_map-0.3.dist-info/top_level.txt
artifact_map-0.3.dist-info/RECORD
