Metadata-Version: 2.1
Name: artifact-map
Version: 0.3
Summary: A short description of your package
Home-page: UNKNOWN
Author: shashankSS1205
Author-email: shashankshekharsingh1205@gmail.com
License: UNKNOWN
Platform: UNKNOWN
Requires-Dist: numpy
Requires-Dist: pandas
